bkash_webhook/__init__.py
bkash_webhook/__version__.py
bkash_webhook/bkash.py
bkash_webhook/commons.py
bkash_webhook/error_codes.py
bkash_webhook/exceptions.py
bkash_webhook/validations.py
tests/__init__.py
tests/test_bkash.py
tests/test_bkashwebhooklistener.py
tests/test_common.py
tests/test_validations.py
bKashWebhook-0.1.1.dist-info/LICENSE
bKashWebhook-0.1.1.dist-info/METADATA
bKashWebhook-0.1.1.dist-info/WHEEL
bKashWebhook-0.1.1.dist-info/top_level.txt
bKashWebhook-0.1.1.dist-info/RECORD
