Metadata-Version: 2.1
Name: bKashWebhook
Version: 0.1.1
Summary: This package will help to receive bKash Webhook payment payload
Home-page: https://github.com/vubon/bkash-webhook
Author: Vubon Roy
Author-email: vubon.roy@gmail.com
License: MIT
Project-URL: Documentation, https://github.com/vubon/bkash-webhook/blob/master/docs/GUIDE.md
Platform: Python
Classifier: License :: OSI Approved :: MIT License
Classifier: Operating System :: OS Independent
Classifier: Intended Audience :: Developers
Classifier: Programming Language :: Python :: 3 :: Only
Classifier: Programming Language :: Python :: 3.6
Classifier: Programming Language :: Python :: 3.7
Classifier: Programming Language :: Python :: 3.8
Classifier: Environment :: Web Environment
Classifier: Topic :: Software Development :: Libraries :: Python Modules
Requires-Dist: requests
Requires-Dist: pyOpenSSL
Requires-Dist: responses
